{
  "id": "npc_sidequest_new_reno_prime_013",
  "type": "side_quest",
  "name": "Ash Mara",
  "region": "new_reno",
  "timelines": [
    "prime"
  ],
  "archetype": "sidequest_region_legend",
  "behaviorPattern": "timeline_observer",
  "dialogPool": "npc_sidequest_new_reno_prime_013_dialog",
  "lootPool": "npc_sidequest_new_reno_prime_013_loot",
  "questHooks": [
    "timeline_warning_01",
    "region_story_02"
  ],
  "anomalyAwareness": 0.77,
  "factionTag": "neutral",
  "notes": "Generated side‑quest NPC with region, timeline, and quest hooks."
}