{
  "id": "npc_sidequest_appalachia_shadow_002",
  "type": "side_quest",
  "name": "Jett Joren",
  "region": "appalachia",
  "timelines": [
    "shadow"
  ],
  "archetype": "sidequest_region_legend",
  "behaviorPattern": "vegas_bound",
  "dialogPool": "npc_sidequest_appalachia_shadow_002_dialog",
  "lootPool": "npc_sidequest_appalachia_shadow_002_loot",
  "questHooks": [
    "timeline_warning_01",
    "fizzcaps_clue_02"
  ],
  "anomalyAwareness": 0.67,
  "factionTag": "neutral",
  "notes": "Generated side‑quest NPC with region, timeline, and quest hooks."
}