{
  "id": "npc_sidequest_appalachia_prime-shadow_014",
  "type": "side_quest",
  "name": "Mara Dax",
  "region": "appalachia",
  "timelines": [
    "prime",
    "shadow"
  ],
  "archetype": "sidequest_fizzcaps_contact",
  "behaviorPattern": "fizzcaps_informer",
  "dialogPool": "npc_sidequest_appalachia_prime-shadow_014_dialog",
  "lootPool": "npc_sidequest_appalachia_prime-shadow_014_loot",
  "questHooks": [
    "region_story_02"
  ],
  "anomalyAwareness": 0.89,
  "factionTag": "neutral",
  "notes": "Generated side‑quest NPC with region, timeline, and quest hooks."
}