{
  "id": "npc_sidequest_mojave_prime_011",
  "type": "side_quest",
  "name": "Nina Varra",
  "region": "mojave",
  "timelines": [
    "prime"
  ],
  "archetype": "sidequest_fizzcaps_contact",
  "behaviorPattern": "timeline_observer",
  "dialogPool": "npc_sidequest_mojave_prime_011_dialog",
  "lootPool": "npc_sidequest_mojave_prime_011_loot",
  "questHooks": [
    "fizzcaps_clue_01",
    "anomaly_investigation_01"
  ],
  "anomalyAwareness": 0.67,
  "factionTag": "neutral",
  "notes": "Generated side‑quest NPC with region, timeline, and quest hooks."
}