{
  "id": "quest_divide_faultline",
  "name": "Faultline",
  "type": "main",
  "poIs": ["Divide Crater", "Storm Ridge", "Collapsed Highway"],
  "description": "Investigate the timeline fractures erupting across the Divide.",
  "objectives": [
    "Survey the crater",
    "Collect storm anomaly readings",
    "Confront the Courier Echo"
  ],
  "endings": [
    {
      "id": "ending_stabilize",
      "description": "You stabilize the fracture.",
      "reward": "Storm‑Tuned Armor",
      "consequence": "Divide storms weaken."
    },
    {
      "id": "ending_amplify",
      "description": "You amplify the fracture.",
      "reward": "Temporal Shard",
      "consequence": "Storms intensify across the Mojave."
    }
  ]
}
