{
  "id": "npc_sidequest_mojave_prime_003",
  "type": "side_quest",
  "name": "Lira Jett",
  "region": "mojave",
  "timelines": [
    "prime"
  ],
  "archetype": "sidequest_traveler",
  "behaviorPattern": "vegas_bound",
  "dialogPool": "npc_sidequest_mojave_prime_003_dialog",
  "lootPool": "npc_sidequest_mojave_prime_003_loot",
  "questHooks": [
    "anomaly_investigation_02",
    "fizzcaps_clue_02"
  ],
  "anomalyAwareness": 0.6,
  "factionTag": "neutral",
  "notes": "Generated side‑quest NPC with region, timeline, and quest hooks."
}